riteaid/__init__.py
riteaid/const.py
riteaid/exceptions.py
riteaid-0.0.9.dist-info/LICENSE
riteaid-0.0.9.dist-info/METADATA
riteaid-0.0.9.dist-info/WHEEL
riteaid-0.0.9.dist-info/top_level.txt
riteaid-0.0.9.dist-info/RECORD
