Metadata-Version: 2.1
Name: riteaid
Version: 0.0.9
Summary: A package to interact with the Rite Aid API
Home-page: https://github.com/IceBotYT/riteaid
Author: IceBotYT
Author-email: icebotyt@outlook.com
License: UNKNOWN
Project-URL: Bug Tracker, https://github.com/IceBotYT/riteaid/issues
Platform: UNKNOWN
Classifier: Programming Language :: Python :: 3
Classifier: License :: OSI Approved :: MIT License
Classifier: Operating System :: OS Independent
Requires-Python: >=3.6
License-File: LICENSE
Requires-Dist: aiohttp
